textwrangler/__init__.py
textwrangler/extract.py
textwrangler/normalize.py
textwrangler/patterns.py
textwrangler/remove.py
textwrangler/replace.py
textwrangler/transform.py
textwrangler-0.0.2.dist-info/LICENSE
textwrangler-0.0.2.dist-info/METADATA
textwrangler-0.0.2.dist-info/WHEEL
textwrangler-0.0.2.dist-info/top_level.txt
textwrangler-0.0.2.dist-info/RECORD
